memotica/__init__.py
memotica/__main__.py
memotica/cli.py
memotica/commands/__init__.py
memotica/commands/export_command.py
memotica/commands/import_command.py
memotica/config.py
memotica/db.py
memotica/deck_tree.py
memotica/flashcards_table.py
memotica/global.tcss
memotica/messages.py
memotica/modals/__init__.py
memotica/modals/add_flashcard_modal.py
memotica/modals/confirm_modal.py
memotica/modals/deck_modal.py
memotica/modals/edit_flashcard_modal.py
memotica/modals/flashcard_modal.py
memotica/modals/help_modal.md
memotica/modals/help_modal.py
memotica/models.py
memotica/repositories.py
memotica/review_screen.py
memotica/sm2.py
memotica/test_repositories.py
memotica/test_sm2.py
memotica/tui.py
memotica-0.5.0.dist-info/LICENSE
memotica-0.5.0.dist-info/METADATA
memotica-0.5.0.dist-info/WHEEL
memotica-0.5.0.dist-info/entry_points.txt
memotica-0.5.0.dist-info/RECORD
