Metadata-Version: 2.1
Name: memotica
Version: 0.5.0
Summary: An easy, fast, and minimalist space repition application for the terminal.
Home-page: https://github.com/dnlzrgz/memotica
License: MIT
Author: dnlzrgz
Author-email: 24715931+dnlzrgz@users.noreply.github.com
Requires-Python: >=3.12,<4.0
Classifier: License :: OSI Approved :: MIT License
Classifier: Programming Language :: Python :: 3
Classifier: Programming Language :: Python :: 3.12
Requires-Dist: click (>=8.1.7,<9.0.0)
Requires-Dist: pandas (>=2.2.2,<3.0.0)
Requires-Dist: sqlalchemy (>=2.0.30,<3.0.0)
Requires-Dist: textual[syntax] (>=0.66.0,<0.67.0)
Project-URL: Documentation, https://github.com/dnlzrgz/memotica
Project-URL: Repository, https://github.com/dnlzrgz/memotica
